huaweicloudsdkrabbitmq/__init__.py
huaweicloudsdkrabbitmq/v2/__init__.py
huaweicloudsdkrabbitmq/v2/rabbitmq_async_client.py
huaweicloudsdkrabbitmq/v2/rabbitmq_client.py
huaweicloudsdkrabbitmq/v2/model/__init__.py
huaweicloudsdkrabbitmq/v2/model/alter_auto_volume_expand_config.py
huaweicloudsdkrabbitmq/v2/model/amqp_user.py
huaweicloudsdkrabbitmq/v2/model/amqp_user_perm.py
huaweicloudsdkrabbitmq/v2/model/batch_create_or_delete_rabbit_mq_tag_request.py
huaweicloudsdkrabbitmq/v2/model/batch_create_or_delete_rabbit_mq_tag_response.py
huaweicloudsdkrabbitmq/v2/model/batch_create_or_delete_tag_req.py
huaweicloudsdkrabbitmq/v2/model/batch_delete_body.py
huaweicloudsdkrabbitmq/v2/model/batch_delete_exchanges_request.py
huaweicloudsdkrabbitmq/v2/model/batch_delete_exchanges_response.py
huaweicloudsdkrabbitmq/v2/model/batch_delete_queues_request.py
huaweicloudsdkrabbitmq/v2/model/batch_delete_queues_response.py
huaweicloudsdkrabbitmq/v2/model/batch_delete_vhosts_request.py
huaweicloudsdkrabbitmq/v2/model/batch_delete_vhosts_response.py
huaweicloudsdkrabbitmq/v2/model/batch_restart_or_delete_instance_req.py
huaweicloudsdkrabbitmq/v2/model/batch_restart_or_delete_instance_resp_results.py
huaweicloudsdkrabbitmq/v2/model/batch_restart_or_delete_instances_request.py
huaweicloudsdkrabbitmq/v2/model/batch_restart_or_delete_instances_response.py
huaweicloudsdkrabbitmq/v2/model/batch_resume_instance_req.py
huaweicloudsdkrabbitmq/v2/model/bindings_details.py
huaweicloudsdkrabbitmq/v2/model/bss_param.py
huaweicloudsdkrabbitmq/v2/model/channel_details.py
huaweicloudsdkrabbitmq/v2/model/consumer_details.py
huaweicloudsdkrabbitmq/v2/model/create_binding_body.py
huaweicloudsdkrabbitmq/v2/model/create_binding_request.py
huaweicloudsdkrabbitmq/v2/model/create_binding_response.py
huaweicloudsdkrabbitmq/v2/model/create_exchange_body.py
huaweicloudsdkrabbitmq/v2/model/create_exchange_request.py
huaweicloudsdkrabbitmq/v2/model/create_exchange_response.py
huaweicloudsdkrabbitmq-3.1.184.dist-info/METADATA
huaweicloudsdkrabbitmq-3.1.184.dist-info/WHEEL
huaweicloudsdkrabbitmq-3.1.184.dist-info/licenses/LICENSE
huaweicloudsdkrabbitmq-3.1.184.dist-info/RECORD
